rlipython/__init__.py
rlipython/completer.py
rlipython/lifecycle.py
rlipython/rlineimpl.py
rlipython/shell.py
rlipython-0.1.2.dist-info/DESCRIPTION.rst
rlipython-0.1.2.dist-info/METADATA
rlipython-0.1.2.dist-info/RECORD
rlipython-0.1.2.dist-info/WHEEL
rlipython-0.1.2.dist-info/metadata.json
rlipython-0.1.2.dist-info/top_level.txt
