Metadata-Version: 2.0
Name: rlipython
Version: 0.1.2
Summary: readline integration for IPython 5.4+ and 6.0+
Home-page: https://github.com/ipython/rlipython
Author: The IPython Development Team
Author-email: ipython-dev@python.org
License: BSD
Platform: UNKNOWN
Requires-Dist: ipython (>5.3)
